{"D\u1ec5": {"play_count": 11, "game_win": 7, "no_mistake": 7, "win_rate": 63.64, "best_time_sec": 25, "best_time_minute": "00:25", "total_time": 329.0, "average_time": "00:47", "current_streak": 0, "best_streak": 7}, "Trung b\u00ecnh": {"play_count": 4, "game_win": 0, "no_mistake": 0, "win_rate": 0, "best_time_sec": null, "best_time_minute": "--:--", "total_time": 0.0, "average_time": "--:--", "current_streak": 0, "best_streak": 0}, "Kh\u00f3": {"play_count": 5, "game_win": 0, "no_mistake": 0, "win_rate": 0, "best_time_sec": null, "best_time_minute": "--:--", "total_time": 0.0, "average_time": "--:--", "current_streak": 0, "best_streak": 0}}